sphinx_openclimate_theme/__init__.py
sphinx_openclimate_theme/_version.py
sphinx_openclimate_theme-0.0.2.dist-info/LICENSE
sphinx_openclimate_theme-0.0.2.dist-info/METADATA
sphinx_openclimate_theme-0.0.2.dist-info/WHEEL
sphinx_openclimate_theme-0.0.2.dist-info/entry_points.txt
sphinx_openclimate_theme-0.0.2.dist-info/top_level.txt
sphinx_openclimate_theme-0.0.2.dist-info/RECORD
